{
  "pretrain": [
    {
      "avg_train_acc": 0.5665823386775123,
      "avg_val_acc": 0.5708473258548312,
      "avg_test_acc": 0.567564093404346,
      "round": 5
    },
    {
      "avg_train_acc": 0.6326718860202365,
      "avg_val_acc": 0.6239116920365227,
      "avg_test_acc": 0.6283362044228448,
      "round": 10
    },
    {
      "avg_train_acc": 0.68746284643809,
      "avg_val_acc": 0.6841461194886101,
      "avg_test_acc": 0.6796523531277975,
      "round": 15
    },
    {
      "avg_train_acc": 0.7510024706522623,
      "avg_val_acc": 0.7330343590842353,
      "avg_test_acc": 0.7424766023953756,
      "round": 20
    },
    {
      "avg_train_acc": 0.763906372918023,
      "avg_val_acc": 0.7464690340889825,
      "avg_test_acc": 0.7434570656882392,
      "round": 25
    },
    {
      "avg_train_acc": 0.7807499700122409,
      "avg_val_acc": 0.7604625225067139,
      "avg_test_acc": 0.7643481824133131,
      "round": 30
    },
    {
      "avg_train_acc": 0.8058260215653313,
      "avg_val_acc": 0.7811284727520413,
      "avg_test_acc": 0.7857467929522196,
      "round": 35
    },
    {
      "avg_train_acc": 0.8102275331815084,
      "avg_val_acc": 0.77590854300393,
      "avg_test_acc": 0.7765754461288452,
      "round": 40
    },
    {
      "avg_train_acc": 0.8056667248407999,
      "avg_val_acc": 0.7748965554767184,
      "avg_test_acc": 0.7794230050510831,
      "round": 45
    },
    {
      "avg_train_acc": 0.8300860789087083,
      "avg_val_acc": 0.790396100944943,
      "avg_test_acc": 0.8023364080323113,
      "round": 50
    },
    {
      "avg_train_acc": 0.8139455980724759,
      "avg_val_acc": 0.7831436660554674,
      "avg_test_acc": 0.7814131710264418,
      "round": 55
    },
    {
      "avg_train_acc": 0.8217447267638313,
      "avg_val_acc": 0.7793862091170417,
      "avg_test_acc": 0.7872773276435004,
      "round": 60
    },
    {
      "avg_train_acc": 0.8395980662769742,
      "avg_val_acc": 0.7979065113597446,
      "avg_test_acc": 0.8041720853911506,
      "round": 65
    },
    {
      "avg_train_acc": 0.8430924150678847,
      "avg_val_acc": 0.7972609533203973,
      "avg_test_acc": 0.794034394952986,
      "round": 70
    },
    {
      "avg_train_acc": 0.8575833439826965,
      "avg_val_acc": 0.8065265946918063,
      "avg_test_acc": 0.8138781852192349,
      "round": 75
    },
    {
      "avg_train_acc": 0.8624448445108202,
      "avg_val_acc": 0.8051539527045356,
      "avg_test_acc": 0.811252044306861,
      "round": 80
    },
    {
      "avg_train_acc": 0.8686482442749871,
      "avg_val_acc": 0.8021691044171652,
      "avg_test_acc": 0.8075868089993795,
      "round": 85
    },
    {
      "avg_train_acc": 0.8744742804103427,
      "avg_val_acc": 0.8046131398942735,
      "avg_test_acc": 0.8139081199963888,
      "round": 90
    },
    {
      "avg_train_acc": 0.8795101841290792,
      "avg_val_acc": 0.8041695356369019,
      "avg_test_acc": 0.8107364243931241,
      "round": 95
    },
    {
      "avg_train_acc": 0.8829037215974596,
      "avg_val_acc": 0.802595423327552,
      "avg_test_acc": 0.8030976918008592,
      "round": 100
    }
  ],
  "unlearn": [],
  "repair": []
}