{
  "data_dir": "E:\\MMFGU\\datasets\\Movies",
  "mode": "unlearning",
  "seeds": [
    42,
    43,
    44
  ],
  "summary": {
    "client_unlearning": {
      "before_avg_val_acc": {
        "mean": 0.4930990626414617,
        "std": 0.014881373644068833
      },
      "before_avg_test_acc": {
        "mean": 0.48100705444812775,
        "std": 0.023584605786143284
      },
      "after_avg_val_acc": {
        "mean": 0.46673499941825863,
        "std": 0.01008186790933447
      },
      "after_avg_test_acc": {
        "mean": 0.4655520111322403,
        "std": 0.010112010190055198
      },
      "delta_avg_val_acc": {
        "mean": -0.026364063223203043,
        "std": 0.005363670330903161
      },
      "delta_avg_test_acc": {
        "mean": -0.015455043315887465,
        "std": 0.022133022601186672
      }
    }
  },
  "summary_pretty": {
    "client_unlearning": {
      "before_avg_val_acc": "49.31 \u00b1 1.49",
      "before_avg_test_acc": "48.10 \u00b1 2.36",
      "after_avg_val_acc": "46.67 \u00b1 1.01",
      "after_avg_test_acc": "46.56 \u00b1 1.01",
      "delta_avg_val_acc": "-2.64 \u00b1 0.54",
      "delta_avg_test_acc": "-1.55 \u00b1 2.21"
    }
  }
}