{
  "pretrain": [
    {
      "avg_train_acc": 0.8874463319778443,
      "avg_val_acc": 0.8845765113830566,
      "avg_test_acc": 0.8844297289848327,
      "round": 10
    },
    {
      "avg_train_acc": 0.9389796257019043,
      "avg_val_acc": 0.937976622581482,
      "avg_test_acc": 0.9367240607738495,
      "round": 20
    },
    {
      "avg_train_acc": 0.9562649667263031,
      "avg_val_acc": 0.9512635111808777,
      "avg_test_acc": 0.95189528465271,
      "round": 30
    },
    {
      "avg_train_acc": 0.9473800182342529,
      "avg_val_acc": 0.9439027726650238,
      "avg_test_acc": 0.9426627993583679,
      "round": 40
    },
    {
      "avg_train_acc": 0.9654056072235108,
      "avg_val_acc": 0.959473478794098,
      "avg_test_acc": 0.9598466455936432,
      "round": 50
    },
    {
      "avg_train_acc": 0.9688260972499847,
      "avg_val_acc": 0.9609516203403473,
      "avg_test_acc": 0.9607263326644897,
      "round": 60
    },
    {
      "avg_train_acc": 0.9707548499107361,
      "avg_val_acc": 0.9622272610664367,
      "avg_test_acc": 0.9611031115055084,
      "round": 70
    },
    {
      "avg_train_acc": 0.982856011390686,
      "avg_val_acc": 0.9711774528026581,
      "avg_test_acc": 0.9712588667869568,
      "round": 80
    },
    {
      "avg_train_acc": 0.9777274787425995,
      "avg_val_acc": 0.9668848931789398,
      "avg_test_acc": 0.965919017791748,
      "round": 90
    },
    {
      "avg_train_acc": 0.9871471941471099,
      "avg_val_acc": 0.9738010108470917,
      "avg_test_acc": 0.9723284721374512,
      "round": 100
    }
  ],
  "reconstruction": [
    {
      "avg_train_acc": 0.9367843137847053,
      "avg_val_acc": 0.9352455735206604,
      "avg_test_acc": 0.9327547748883566,
      "round": 20
    },
    {
      "avg_train_acc": 0.9649453229374356,
      "avg_val_acc": 0.9597764280107286,
      "avg_test_acc": 0.959237171543969,
      "round": 40
    },
    {
      "avg_train_acc": 0.97010162141588,
      "avg_val_acc": 0.960175547334883,
      "avg_test_acc": 0.9609807994630601,
      "round": 60
    },
    {
      "avg_train_acc": 0.9783455597029792,
      "avg_val_acc": 0.9662597311867608,
      "avg_test_acc": 0.9653588069809808,
      "round": 80
    },
    {
      "avg_train_acc": 0.9737971822420756,
      "avg_val_acc": 0.9623307387034098,
      "avg_test_acc": 0.9608346621195475,
      "round": 100
    }
  ]
}