{
  "pretrain": [
    {
      "avg_train_acc": 0.8163528561592102,
      "avg_val_acc": 0.8151833236217498,
      "avg_test_acc": 0.8127550482749939,
      "round": 5
    },
    {
      "avg_train_acc": 0.8980054974555969,
      "avg_val_acc": 0.8915085673332215,
      "avg_test_acc": 0.8975019752979279,
      "round": 10
    },
    {
      "avg_train_acc": 0.9449312090873718,
      "avg_val_acc": 0.9374905586242676,
      "avg_test_acc": 0.9426601886749267,
      "round": 15
    },
    {
      "avg_train_acc": 0.9469376385211945,
      "avg_val_acc": 0.9340027332305908,
      "avg_test_acc": 0.9381268084049225,
      "round": 20
    },
    {
      "avg_train_acc": 0.9671441316604614,
      "avg_val_acc": 0.9488013923168183,
      "avg_test_acc": 0.9559098422527313,
      "round": 25
    },
    {
      "avg_train_acc": 0.9726401388645172,
      "avg_val_acc": 0.9480985581874848,
      "avg_test_acc": 0.9519109785556793,
      "round": 30
    },
    {
      "avg_train_acc": 0.9787951707839966,
      "avg_val_acc": 0.9568663418293,
      "avg_test_acc": 0.9591309189796448,
      "round": 35
    },
    {
      "avg_train_acc": 0.9860551595687866,
      "avg_val_acc": 0.9581457257270813,
      "avg_test_acc": 0.9592199683189392,
      "round": 40
    },
    {
      "avg_train_acc": 0.9860301971435547,
      "avg_val_acc": 0.9573080480098725,
      "avg_test_acc": 0.9627454221248627,
      "round": 45
    },
    {
      "avg_train_acc": 0.9891954123973846,
      "avg_val_acc": 0.9581137478351593,
      "avg_test_acc": 0.9579596877098083,
      "round": 50
    },
    {
      "avg_train_acc": 0.9897107183933258,
      "avg_val_acc": 0.9632027864456176,
      "avg_test_acc": 0.9649214327335358,
      "round": 55
    },
    {
      "avg_train_acc": 0.991300356388092,
      "avg_val_acc": 0.9606870412826538,
      "avg_test_acc": 0.9581335604190826,
      "round": 60
    },
    {
      "avg_train_acc": 0.9921353757381439,
      "avg_val_acc": 0.962940514087677,
      "avg_test_acc": 0.9668097019195556,
      "round": 65
    },
    {
      "avg_train_acc": 0.994546639919281,
      "avg_val_acc": 0.9603622198104859,
      "avg_test_acc": 0.9614187180995941,
      "round": 70
    },
    {
      "avg_train_acc": 0.9928703606128693,
      "avg_val_acc": 0.963249397277832,
      "avg_test_acc": 0.9636067807674408,
      "round": 75
    },
    {
      "avg_train_acc": 0.9952810704708099,
      "avg_val_acc": 0.9607366025447845,
      "avg_test_acc": 0.959105658531189,
      "round": 80
    },
    {
      "avg_train_acc": 0.9935054063796998,
      "avg_val_acc": 0.9632473945617676,
      "avg_test_acc": 0.9658485054969788,
      "round": 85
    },
    {
      "avg_train_acc": 0.9971754014492035,
      "avg_val_acc": 0.9622605621814728,
      "avg_test_acc": 0.9614316880702972,
      "round": 90
    },
    {
      "avg_train_acc": 0.9956051468849182,
      "avg_val_acc": 0.9633535802364349,
      "avg_test_acc": 0.9633383929729462,
      "round": 95
    },
    {
      "avg_train_acc": 0.9984335362911224,
      "avg_val_acc": 0.9597684025764466,
      "avg_test_acc": 0.9611622273921967,
      "round": 100
    }
  ],
  "distill": [
    {
      "avg_train_acc": 0.9977038323879241,
      "avg_val_acc": 0.9597582876682281,
      "avg_test_acc": 0.9585358917713165,
      "epoch": 1,
      "distill_loss": 0.08611441714068253
    },
    {
      "avg_train_acc": 0.9976965129375458,
      "avg_val_acc": 0.9635301411151886,
      "avg_test_acc": 0.9632649302482605,
      "epoch": 2,
      "distill_loss": 0.066072266548872
    },
    {
      "avg_train_acc": 0.9981161713600158,
      "avg_val_acc": 0.9590974271297454,
      "avg_test_acc": 0.9629562020301818,
      "epoch": 3,
      "distill_loss": 0.05961352545354101
    },
    {
      "avg_train_acc": 0.9981147408485412,
      "avg_val_acc": 0.9609775900840759,
      "avg_test_acc": 0.9591903209686279,
      "epoch": 4,
      "distill_loss": 0.04217582713398668
    },
    {
      "avg_train_acc": 0.9984334290027619,
      "avg_val_acc": 0.9628522753715515,
      "avg_test_acc": 0.9626944363117218,
      "epoch": 5,
      "distill_loss": 0.03194308570689625
    },
    {
      "avg_train_acc": 0.9984332144260406,
      "avg_val_acc": 0.9623033821582794,
      "avg_test_acc": 0.9623978912830353,
      "epoch": 6,
      "distill_loss": 0.02995267179277208
    },
    {
      "avg_train_acc": 0.9984332144260406,
      "avg_val_acc": 0.9615973353385925,
      "avg_test_acc": 0.9620350301265717,
      "epoch": 7,
      "distill_loss": 0.028149079738391772
    },
    {
      "avg_train_acc": 0.9984317600727082,
      "avg_val_acc": 0.9610964775085449,
      "avg_test_acc": 0.9611440420150756,
      "epoch": 8,
      "distill_loss": 0.026767538239558537
    }
  ],
  "retrain": []
}