{
  "pretrain": [
    {
      "avg_train_acc": 0.8659017443656921,
      "avg_val_acc": 0.8680440127849579,
      "avg_test_acc": 0.8650407731533051,
      "round": 5
    },
    {
      "avg_train_acc": 0.9067846953868866,
      "avg_val_acc": 0.9076740980148316,
      "avg_test_acc": 0.9071187615394593,
      "round": 10
    },
    {
      "avg_train_acc": 0.9303910553455352,
      "avg_val_acc": 0.9306542873382568,
      "avg_test_acc": 0.9284624814987182,
      "round": 15
    },
    {
      "avg_train_acc": 0.9374364256858826,
      "avg_val_acc": 0.9392423629760742,
      "avg_test_acc": 0.9373452126979828,
      "round": 20
    },
    {
      "avg_train_acc": 0.9569569885730743,
      "avg_val_acc": 0.9549076139926911,
      "avg_test_acc": 0.9514070868492126,
      "round": 25
    },
    {
      "avg_train_acc": 0.9617274582386017,
      "avg_val_acc": 0.9596566498279572,
      "avg_test_acc": 0.9583113610744476,
      "round": 30
    },
    {
      "avg_train_acc": 0.9618299126625061,
      "avg_val_acc": 0.9582976937294007,
      "avg_test_acc": 0.9565974354743958,
      "round": 35
    },
    {
      "avg_train_acc": 0.9614446938037873,
      "avg_val_acc": 0.9562545657157898,
      "avg_test_acc": 0.9564309656620026,
      "round": 40
    },
    {
      "avg_train_acc": 0.9685316503047943,
      "avg_val_acc": 0.9637768685817718,
      "avg_test_acc": 0.9620457291603088,
      "round": 45
    },
    {
      "avg_train_acc": 0.9703408300876617,
      "avg_val_acc": 0.9609266877174377,
      "avg_test_acc": 0.9608022034168243,
      "round": 50
    },
    {
      "avg_train_acc": 0.9780162870883942,
      "avg_val_acc": 0.9697173178195954,
      "avg_test_acc": 0.9695112526416778,
      "round": 55
    },
    {
      "avg_train_acc": 0.9764864981174469,
      "avg_val_acc": 0.9660611629486084,
      "avg_test_acc": 0.966204047203064,
      "round": 60
    },
    {
      "avg_train_acc": 0.9792076110839844,
      "avg_val_acc": 0.9699826657772064,
      "avg_test_acc": 0.9693117082118988,
      "round": 65
    },
    {
      "avg_train_acc": 0.9798422574996948,
      "avg_val_acc": 0.9679824829101562,
      "avg_test_acc": 0.9678735733032227,
      "round": 70
    },
    {
      "avg_train_acc": 0.9817501544952393,
      "avg_val_acc": 0.9705294966697693,
      "avg_test_acc": 0.9694549739360809,
      "round": 75
    },
    {
      "avg_train_acc": 0.9797597467899323,
      "avg_val_acc": 0.9677043437957764,
      "avg_test_acc": 0.9671566009521484,
      "round": 80
    },
    {
      "avg_train_acc": 0.9841992557048798,
      "avg_val_acc": 0.9717192709445953,
      "avg_test_acc": 0.9703210830688477,
      "round": 85
    },
    {
      "avg_train_acc": 0.9807640314102173,
      "avg_val_acc": 0.969555401802063,
      "avg_test_acc": 0.9681409955024719,
      "round": 90
    },
    {
      "avg_train_acc": 0.9842539966106415,
      "avg_val_acc": 0.9702486634254456,
      "avg_test_acc": 0.9683719158172608,
      "round": 95
    },
    {
      "avg_train_acc": 0.9789706230163574,
      "avg_val_acc": 0.9657743573188782,
      "avg_test_acc": 0.9638091385364532,
      "round": 100
    }
  ],
  "unlearn": [
    {
      "avg_train_acc": 0.9811655938625335,
      "avg_val_acc": 0.9667290925979615,
      "avg_test_acc": 0.9636072516441345,
      "epoch": 1
    },
    {
      "avg_train_acc": 0.9794429063796997,
      "avg_val_acc": 0.9664114415645599,
      "avg_test_acc": 0.9632561564445495,
      "epoch": 2
    },
    {
      "avg_train_acc": 0.9799760162830353,
      "avg_val_acc": 0.9675140082836151,
      "avg_test_acc": 0.9640160262584686,
      "epoch": 3
    },
    {
      "avg_train_acc": 0.9820450186729431,
      "avg_val_acc": 0.9688872933387757,
      "avg_test_acc": 0.9663105010986328,
      "epoch": 4
    },
    {
      "avg_train_acc": 0.9834275484085083,
      "avg_val_acc": 0.9698480427265167,
      "avg_test_acc": 0.9679490208625794,
      "epoch": 5
    },
    {
      "avg_train_acc": 0.9841415166854859,
      "avg_val_acc": 0.9706285834312439,
      "avg_test_acc": 0.9688625276088715,
      "epoch": 6
    },
    {
      "avg_train_acc": 0.9843116104602814,
      "avg_val_acc": 0.9722177386283875,
      "avg_test_acc": 0.9683111727237701,
      "epoch": 7
    },
    {
      "avg_train_acc": 0.9812900066375733,
      "avg_val_acc": 0.9683968126773834,
      "avg_test_acc": 0.9640150010585785,
      "epoch": 8
    },
    {
      "avg_train_acc": 0.9787674903869629,
      "avg_val_acc": 0.9653922915458679,
      "avg_test_acc": 0.9623840928077698,
      "epoch": 9
    },
    {
      "avg_train_acc": 0.9791085481643677,
      "avg_val_acc": 0.9655927121639252,
      "avg_test_acc": 0.9628443419933319,
      "epoch": 10
    }
  ],
  "repair": [
    {
      "avg_train_acc": 0.9803358647558424,
      "avg_val_acc": 0.9662157032224867,
      "avg_test_acc": 0.9651671846707662,
      "round": 1
    },
    {
      "avg_train_acc": 0.9825507866011726,
      "avg_val_acc": 0.9692253139283922,
      "avg_test_acc": 0.9658561084005568,
      "round": 2
    }
  ]
}