{
  "pretrain": [
    {
      "avg_train_acc": 0.13795786201953888,
      "avg_val_acc": 0.13282345049083233,
      "avg_test_acc": 0.13617511168122293,
      "round": 1
    },
    {
      "avg_train_acc": 0.13588222712278367,
      "avg_val_acc": 0.1322132371366024,
      "avg_test_acc": 0.1309141717851162,
      "round": 2
    },
    {
      "avg_train_acc": 0.44178986847400664,
      "avg_val_acc": 0.445815846323967,
      "avg_test_acc": 0.44193573892116544,
      "round": 3
    },
    {
      "avg_train_acc": 0.3030179500579834,
      "avg_val_acc": 0.2996800050139427,
      "avg_test_acc": 0.29915924519300463,
      "round": 4
    },
    {
      "avg_train_acc": 0.4997901260852814,
      "avg_val_acc": 0.5083039969205856,
      "avg_test_acc": 0.5078605115413666,
      "round": 5
    },
    {
      "avg_train_acc": 0.3830996811389923,
      "avg_val_acc": 0.3811416894197464,
      "avg_test_acc": 0.3817430943250656,
      "round": 6
    },
    {
      "avg_train_acc": 0.461584010720253,
      "avg_val_acc": 0.46087186932563784,
      "avg_test_acc": 0.46515917479991914,
      "round": 7
    },
    {
      "avg_train_acc": 0.4031173139810562,
      "avg_val_acc": 0.40869528353214263,
      "avg_test_acc": 0.3996782243251801,
      "round": 8
    },
    {
      "avg_train_acc": 0.5149814039468765,
      "avg_val_acc": 0.5090261280536652,
      "avg_test_acc": 0.5098372906446457,
      "round": 9
    },
    {
      "avg_train_acc": 0.5344842582941055,
      "avg_val_acc": 0.5363502681255341,
      "avg_test_acc": 0.5265372633934021,
      "round": 10
    },
    {
      "avg_train_acc": 0.5769345730543136,
      "avg_val_acc": 0.5728245913982392,
      "avg_test_acc": 0.5727686733007431,
      "round": 11
    },
    {
      "avg_train_acc": 0.6231324583292007,
      "avg_val_acc": 0.6194774150848389,
      "avg_test_acc": 0.6155592888593674,
      "round": 12
    },
    {
      "avg_train_acc": 0.6077160984277725,
      "avg_val_acc": 0.5962740838527679,
      "avg_test_acc": 0.606067442893982,
      "round": 13
    },
    {
      "avg_train_acc": 0.6625383377075196,
      "avg_val_acc": 0.6624988198280335,
      "avg_test_acc": 0.6583545565605163,
      "round": 14
    },
    {
      "avg_train_acc": 0.6320224642753601,
      "avg_val_acc": 0.618976640701294,
      "avg_test_acc": 0.6303089380264282,
      "round": 15
    },
    {
      "avg_train_acc": 0.6872795283794403,
      "avg_val_acc": 0.6803030252456665,
      "avg_test_acc": 0.6795970439910889,
      "round": 16
    },
    {
      "avg_train_acc": 0.6652063429355621,
      "avg_val_acc": 0.6518717586994172,
      "avg_test_acc": 0.6587619364261628,
      "round": 17
    },
    {
      "avg_train_acc": 0.6983270883560181,
      "avg_val_acc": 0.6901760935783386,
      "avg_test_acc": 0.6853336453437805,
      "round": 18
    },
    {
      "avg_train_acc": 0.684871393442154,
      "avg_val_acc": 0.6703046321868896,
      "avg_test_acc": 0.6764998137950897,
      "round": 19
    },
    {
      "avg_train_acc": 0.6994194924831391,
      "avg_val_acc": 0.6950348138809204,
      "avg_test_acc": 0.6884673297405243,
      "round": 20
    },
    {
      "avg_train_acc": 0.7042910933494568,
      "avg_val_acc": 0.6847004055976867,
      "avg_test_acc": 0.6884614616632462,
      "round": 21
    },
    {
      "avg_train_acc": 0.7017389178276062,
      "avg_val_acc": 0.6971886575222015,
      "avg_test_acc": 0.6965077757835388,
      "round": 22
    },
    {
      "avg_train_acc": 0.71488236784935,
      "avg_val_acc": 0.6988154590129853,
      "avg_test_acc": 0.6961738348007203,
      "round": 23
    },
    {
      "avg_train_acc": 0.7104915320873261,
      "avg_val_acc": 0.6977369666099549,
      "avg_test_acc": 0.7076379656791687,
      "round": 24
    },
    {
      "avg_train_acc": 0.7250903487205506,
      "avg_val_acc": 0.7119592308998108,
      "avg_test_acc": 0.7060522377490998,
      "round": 25
    },
    {
      "avg_train_acc": 0.7298314809799195,
      "avg_val_acc": 0.7102637231349945,
      "avg_test_acc": 0.7242104291915894,
      "round": 26
    },
    {
      "avg_train_acc": 0.737075686454773,
      "avg_val_acc": 0.7216987133026123,
      "avg_test_acc": 0.7187623083591461,
      "round": 27
    },
    {
      "avg_train_acc": 0.7412832617759705,
      "avg_val_acc": 0.7230933666229248,
      "avg_test_acc": 0.7356978356838226,
      "round": 28
    },
    {
      "avg_train_acc": 0.748436015844345,
      "avg_val_acc": 0.729906415939331,
      "avg_test_acc": 0.7330607950687409,
      "round": 29
    },
    {
      "avg_train_acc": 0.7531607806682586,
      "avg_val_acc": 0.7319689333438874,
      "avg_test_acc": 0.7481177687644959,
      "round": 30
    },
    {
      "avg_train_acc": 0.755215173959732,
      "avg_val_acc": 0.7355506658554077,
      "avg_test_acc": 0.7388908326625824,
      "round": 31
    },
    {
      "avg_train_acc": 0.768030196428299,
      "avg_val_acc": 0.7464931726455688,
      "avg_test_acc": 0.7550862252712249,
      "round": 32
    },
    {
      "avg_train_acc": 0.7633461713790893,
      "avg_val_acc": 0.7482760369777679,
      "avg_test_acc": 0.747603178024292,
      "round": 33
    },
    {
      "avg_train_acc": 0.7685896217823028,
      "avg_val_acc": 0.7487265408039093,
      "avg_test_acc": 0.7553601324558258,
      "round": 34
    },
    {
      "avg_train_acc": 0.7713584542274475,
      "avg_val_acc": 0.7547878682613373,
      "avg_test_acc": 0.7526442468166351,
      "round": 35
    },
    {
      "avg_train_acc": 0.7816219508647919,
      "avg_val_acc": 0.7583208918571472,
      "avg_test_acc": 0.761509644985199,
      "round": 36
    },
    {
      "avg_train_acc": 0.7840127766132354,
      "avg_val_acc": 0.7635017514228821,
      "avg_test_acc": 0.7620514810085297,
      "round": 37
    },
    {
      "avg_train_acc": 0.7915605783462525,
      "avg_val_acc": 0.7641580641269684,
      "avg_test_acc": 0.768184769153595,
      "round": 38
    },
    {
      "avg_train_acc": 0.7900272250175476,
      "avg_val_acc": 0.7659297943115234,
      "avg_test_acc": 0.7684860050678253,
      "round": 39
    },
    {
      "avg_train_acc": 0.7954010248184205,
      "avg_val_acc": 0.7704809546470642,
      "avg_test_acc": 0.7687507808208466,
      "round": 40
    },
    {
      "avg_train_acc": 0.7937370061874389,
      "avg_val_acc": 0.7682922959327698,
      "avg_test_acc": 0.7710745453834533,
      "round": 41
    },
    {
      "avg_train_acc": 0.7951929211616516,
      "avg_val_acc": 0.7675748586654663,
      "avg_test_acc": 0.7624312758445739,
      "round": 42
    },
    {
      "avg_train_acc": 0.7986883044242858,
      "avg_val_acc": 0.76940016746521,
      "avg_test_acc": 0.7737689018249512,
      "round": 43
    },
    {
      "avg_train_acc": 0.8000090420246124,
      "avg_val_acc": 0.775128698348999,
      "avg_test_acc": 0.7705657541751861,
      "round": 44
    },
    {
      "avg_train_acc": 0.800629723072052,
      "avg_val_acc": 0.768731313943863,
      "avg_test_acc": 0.771291708946228,
      "round": 45
    },
    {
      "avg_train_acc": 0.8017325580120087,
      "avg_val_acc": 0.7720302641391754,
      "avg_test_acc": 0.7711886823177337,
      "round": 46
    },
    {
      "avg_train_acc": 0.8035553991794586,
      "avg_val_acc": 0.7753294467926025,
      "avg_test_acc": 0.7754851400852203,
      "round": 47
    },
    {
      "avg_train_acc": 0.79809929728508,
      "avg_val_acc": 0.7655818700790405,
      "avg_test_acc": 0.7706586658954621,
      "round": 48
    },
    {
      "avg_train_acc": 0.8030897498130798,
      "avg_val_acc": 0.7743062674999237,
      "avg_test_acc": 0.7678291380405426,
      "round": 49
    },
    {
      "avg_train_acc": 0.8070463359355926,
      "avg_val_acc": 0.7751139223575592,
      "avg_test_acc": 0.775494647026062,
      "round": 50
    },
    {
      "avg_train_acc": 0.8133570671081543,
      "avg_val_acc": 0.776267808675766,
      "avg_test_acc": 0.7756180346012116,
      "round": 51
    },
    {
      "avg_train_acc": 0.8150845229625702,
      "avg_val_acc": 0.7803427457809449,
      "avg_test_acc": 0.779503983259201,
      "round": 52
    },
    {
      "avg_train_acc": 0.8122148931026458,
      "avg_val_acc": 0.7733616948127746,
      "avg_test_acc": 0.7721767127513885,
      "round": 53
    },
    {
      "avg_train_acc": 0.8167701065540314,
      "avg_val_acc": 0.781626570224762,
      "avg_test_acc": 0.7866916537284852,
      "round": 54
    },
    {
      "avg_train_acc": 0.811007285118103,
      "avg_val_acc": 0.7707954347133636,
      "avg_test_acc": 0.7683329403400421,
      "round": 55
    },
    {
      "avg_train_acc": 0.8126044034957886,
      "avg_val_acc": 0.7780761480331421,
      "avg_test_acc": 0.7820897102355957,
      "round": 56
    },
    {
      "avg_train_acc": 0.8131140351295472,
      "avg_val_acc": 0.772395795583725,
      "avg_test_acc": 0.7703779339790344,
      "round": 57
    },
    {
      "avg_train_acc": 0.8194831430912017,
      "avg_val_acc": 0.7828944385051727,
      "avg_test_acc": 0.7876958608627319,
      "round": 58
    },
    {
      "avg_train_acc": 0.8143280684947968,
      "avg_val_acc": 0.7756432831287384,
      "avg_test_acc": 0.7745200216770172,
      "round": 59
    },
    {
      "avg_train_acc": 0.8162924587726593,
      "avg_val_acc": 0.7802592158317566,
      "avg_test_acc": 0.7846000671386719,
      "round": 60
    },
    {
      "avg_train_acc": 0.817717844247818,
      "avg_val_acc": 0.7755281507968903,
      "avg_test_acc": 0.7757583558559418,
      "round": 61
    },
    {
      "avg_train_acc": 0.822916853427887,
      "avg_val_acc": 0.782680481672287,
      "avg_test_acc": 0.7883595824241638,
      "round": 62
    },
    {
      "avg_train_acc": 0.8216641247272491,
      "avg_val_acc": 0.7792413651943206,
      "avg_test_acc": 0.7804642736911773,
      "round": 63
    },
    {
      "avg_train_acc": 0.8260238349437714,
      "avg_val_acc": 0.7903436958789826,
      "avg_test_acc": 0.7863997519016266,
      "round": 64
    },
    {
      "avg_train_acc": 0.827711308002472,
      "avg_val_acc": 0.7800236105918884,
      "avg_test_acc": 0.7841768562793732,
      "round": 65
    },
    {
      "avg_train_acc": 0.8337323188781738,
      "avg_val_acc": 0.791128671169281,
      "avg_test_acc": 0.7933343470096588,
      "round": 66
    },
    {
      "avg_train_acc": 0.8184846699237823,
      "avg_val_acc": 0.772511613368988,
      "avg_test_acc": 0.7737586259841919,
      "round": 67
    },
    {
      "avg_train_acc": 0.8328903257846832,
      "avg_val_acc": 0.7850828170776367,
      "avg_test_acc": 0.7981583476066589,
      "round": 68
    },
    {
      "avg_train_acc": 0.8239159107208252,
      "avg_val_acc": 0.7758067429065705,
      "avg_test_acc": 0.777356106042862,
      "round": 69
    },
    {
      "avg_train_acc": 0.8296294629573822,
      "avg_val_acc": 0.7807948410511016,
      "avg_test_acc": 0.7883721888065338,
      "round": 70
    },
    {
      "avg_train_acc": 0.8303320586681366,
      "avg_val_acc": 0.7784804046154022,
      "avg_test_acc": 0.7783315300941467,
      "round": 71
    },
    {
      "avg_train_acc": 0.8282586634159088,
      "avg_val_acc": 0.7818005681037903,
      "avg_test_acc": 0.788075977563858,
      "round": 72
    },
    {
      "avg_train_acc": 0.8318877875804901,
      "avg_val_acc": 0.7787371516227722,
      "avg_test_acc": 0.7742948114871979,
      "round": 73
    },
    {
      "avg_train_acc": 0.8310345470905304,
      "avg_val_acc": 0.7845005869865418,
      "avg_test_acc": 0.7871682226657868,
      "round": 74
    },
    {
      "avg_train_acc": 0.8459830760955811,
      "avg_val_acc": 0.7919193744659424,
      "avg_test_acc": 0.789672726392746,
      "round": 75
    },
    {
      "avg_train_acc": 0.8412083446979522,
      "avg_val_acc": 0.7924780547618866,
      "avg_test_acc": 0.7955339014530182,
      "round": 76
    },
    {
      "avg_train_acc": 0.842396593093872,
      "avg_val_acc": 0.7864389300346375,
      "avg_test_acc": 0.7845979392528534,
      "round": 77
    },
    {
      "avg_train_acc": 0.8422757685184479,
      "avg_val_acc": 0.7908272802829742,
      "avg_test_acc": 0.7853676974773407,
      "round": 78
    },
    {
      "avg_train_acc": 0.8500098407268524,
      "avg_val_acc": 0.7930936098098755,
      "avg_test_acc": 0.7974887192249298,
      "round": 79
    },
    {
      "avg_train_acc": 0.8490947961807251,
      "avg_val_acc": 0.7969836950302124,
      "avg_test_acc": 0.7923834443092346,
      "round": 80
    },
    {
      "avg_train_acc": 0.8509033501148224,
      "avg_val_acc": 0.7901749789714814,
      "avg_test_acc": 0.7956598043441773,
      "round": 81
    },
    {
      "avg_train_acc": 0.8541389346122742,
      "avg_val_acc": 0.7972303748130798,
      "avg_test_acc": 0.7948751628398896,
      "round": 82
    },
    {
      "avg_train_acc": 0.852749514579773,
      "avg_val_acc": 0.7933080852031708,
      "avg_test_acc": 0.7965985834598541,
      "round": 83
    },
    {
      "avg_train_acc": 0.8504289925098419,
      "avg_val_acc": 0.7891883254051208,
      "avg_test_acc": 0.7833625674247742,
      "round": 84
    },
    {
      "avg_train_acc": 0.8568564116954803,
      "avg_val_acc": 0.8012891471385956,
      "avg_test_acc": 0.7976185023784638,
      "round": 85
    },
    {
      "avg_train_acc": 0.861970180273056,
      "avg_val_acc": 0.7909351527690888,
      "avg_test_acc": 0.7867304682731628,
      "round": 86
    },
    {
      "avg_train_acc": 0.8631066679954529,
      "avg_val_acc": 0.8035381317138672,
      "avg_test_acc": 0.8050443649291992,
      "round": 87
    },
    {
      "avg_train_acc": 0.8609882235527039,
      "avg_val_acc": 0.7921151518821716,
      "avg_test_acc": 0.783170735836029,
      "round": 88
    },
    {
      "avg_train_acc": 0.8629103541374207,
      "avg_val_acc": 0.7989641845226287,
      "avg_test_acc": 0.802968192100525,
      "round": 89
    },
    {
      "avg_train_acc": 0.8689630925655365,
      "avg_val_acc": 0.7921310424804687,
      "avg_test_acc": 0.7854927539825439,
      "round": 90
    },
    {
      "avg_train_acc": 0.8689574778079987,
      "avg_val_acc": 0.8031799495220184,
      "avg_test_acc": 0.8066483616828919,
      "round": 91
    },
    {
      "avg_train_acc": 0.8669580698013306,
      "avg_val_acc": 0.7863574683666229,
      "avg_test_acc": 0.781981211900711,
      "round": 92
    },
    {
      "avg_train_acc": 0.8683468639850617,
      "avg_val_acc": 0.7988827943801879,
      "avg_test_acc": 0.8041009306907654,
      "round": 93
    },
    {
      "avg_train_acc": 0.8587742269039154,
      "avg_val_acc": 0.7875561594963074,
      "avg_test_acc": 0.7791967630386353,
      "round": 94
    },
    {
      "avg_train_acc": 0.8727878212928772,
      "avg_val_acc": 0.7997617602348328,
      "avg_test_acc": 0.8023263275623321,
      "round": 95
    },
    {
      "avg_train_acc": 0.8628847897052765,
      "avg_val_acc": 0.7879933476448059,
      "avg_test_acc": 0.7865132689476013,
      "round": 96
    },
    {
      "avg_train_acc": 0.8676304042339325,
      "avg_val_acc": 0.8006568431854248,
      "avg_test_acc": 0.7958892703056335,
      "round": 97
    },
    {
      "avg_train_acc": 0.8602005183696747,
      "avg_val_acc": 0.783162122964859,
      "avg_test_acc": 0.7812968313694,
      "round": 98
    },
    {
      "avg_train_acc": 0.8696633875370026,
      "avg_val_acc": 0.7977775454521179,
      "avg_test_acc": 0.7925211191177368,
      "round": 99
    },
    {
      "avg_train_acc": 0.8598228573799134,
      "avg_val_acc": 0.7807158052921295,
      "avg_test_acc": 0.7844698846340179,
      "round": 100
    }
  ],
  "purge": []
}